mcsrranked/__init__.py
mcsrranked/_base_client.py
mcsrranked/_client.py
mcsrranked/_constants.py
mcsrranked/_exceptions.py
mcsrranked/_types.py
mcsrranked/py.typed
mcsrranked/resources/__init__.py
mcsrranked/resources/leaderboards.py
mcsrranked/resources/live.py
mcsrranked/resources/matches.py
mcsrranked/resources/users.py
mcsrranked/resources/weekly_races.py
mcsrranked/types/__init__.py
mcsrranked/types/leaderboard.py
mcsrranked/types/live.py
mcsrranked/types/match.py
mcsrranked/types/shared.py
mcsrranked/types/user.py
mcsrranked/types/weekly_race.py
mcsrranked-0.2.0.dist-info/METADATA
mcsrranked-0.2.0.dist-info/WHEEL
mcsrranked-0.2.0.dist-info/licenses/LICENSE
mcsrranked-0.2.0.dist-info/RECORD
