Metadata-Version: 2.4
Name: mcsrranked
Version: 0.2.0
Summary: Python SDK for the MCSR Ranked API
Project-URL: Homepage, https://github.com/camodotgg/mcsrranked-python
Project-URL: Documentation, https://camodotgg.github.io/mcsrranked-python
Project-URL: Repository, https://github.com/camodotgg/mcsrranked-python
Author-email: Camo <camodotgg@gmail.com>
License-Expression: MIT
License-File: LICENSE
Keywords: api,mcsr,mcsr ranked,python,sdk
Classifier: Development Status :: 4 - Beta
Classifier: Intended Audience :: Developers
Classifier: License :: OSI Approved :: MIT License
Classifier: Programming Language :: Python :: 3
Classifier: Programming Language :: Python :: 3.11
Classifier: Programming Language :: Python :: 3.12
Classifier: Programming Language :: Python :: 3.13
Classifier: Typing :: Typed
Requires-Python: >=3.11
Requires-Dist: httpx>=0.27.0
Requires-Dist: pydantic>=2.0.0
Provides-Extra: dev
Requires-Dist: mypy>=1.13.0; extra == 'dev'
Requires-Dist: pre-commit>=4.0.0; extra == 'dev'
Requires-Dist: pytest-asyncio>=0.24.0; extra == 'dev'
Requires-Dist: pytest>=8.0.0; extra == 'dev'
Requires-Dist: respx>=0.21.0; extra == 'dev'
Requires-Dist: ruff>=0.8.0; extra == 'dev'
Provides-Extra: docs
Requires-Dist: griffe-pydantic>=1.0.0; extra == 'docs'
Requires-Dist: mkdocs-material>=9.5.0; extra == 'docs'
Requires-Dist: mkdocs>=1.6.0; extra == 'docs'
Requires-Dist: mkdocstrings[python]>=0.27.0; extra == 'docs'
